clump_history/__init__.py
clump_history/__main__.py
clump_history/cli.py
clump_history/fit.py
clump_history/gui.py
clump_history/io.py
clump_history/model.py
clump_history/plot.py
clump_history/run_cli.py
clump_history/dist/clump-history/IPython/extensions/__init__.py
clump_history/dist/clump-history/IPython/extensions/autoreload.py
clump_history/dist/clump-history/IPython/extensions/cythonmagic.py
clump_history/dist/clump-history/IPython/extensions/rmagic.py
clump_history/dist/clump-history/IPython/extensions/storemagic.py
clump_history/dist/clump-history/IPython/extensions/sympyprinting.py
clump_history/dist/clump-history/IPython/extensions/tests/__init__.py
clump_history/dist/clump-history/IPython/extensions/tests/test_autoreload.py
clump_history/dist/clump-history/IPython/extensions/tests/test_storemagic.py
clump_history-0.1.0.dist-info/METADATA
clump_history-0.1.0.dist-info/WHEEL
clump_history-0.1.0.dist-info/entry_points.txt
clump_history-0.1.0.dist-info/top_level.txt
clump_history-0.1.0.dist-info/RECORD
