Metadata-Version: 2.1
Name: clump-history
Version: 0.1.0
Summary: Forward modeling clumped isotope Δ47 along thermal histories (isotopylog).
Author: Keran Li
License: MIT
Requires-Python: >=3.7
Requires-Dist: numpy
Requires-Dist: pandas
Requires-Dist: matplotlib
Requires-Dist: scipy
Requires-Dist: isotopylog
